bitcode/__init__.py
bitcode/console.py
bitcode-1.10.dist-info/METADATA
bitcode-1.10.dist-info/WHEEL
bitcode-1.10.dist-info/RECORD
